{
  "type": "playbook",
  "spec_version": "cacao-2.0",
  "id": "playbook--611b80a5-161d-494b-8683-7fd72448052a",
  "name": "SOC Response Playbook — Incident c141c1bf-a05a-43a2-83d6-66516af2146a",
  "description": "SUMMARY: A HIGH-severity PROCESS_SPAWN alert was triggered\nfrom 192.168.1.32 with 70% confidence.\nTECHNIQUE: Suspicious activity detected via unknown pattern (T1059).\nACTION: ISOLATE_HOST",
  "created": "2026-04-03T20:17:30.518567+00:00",
  "modified": "2026-04-03T20:17:30.518592+00:00",
  "created_by": "identity--35c48b0a-7c80-4725-858d-a08b9f7dd85c",
  "playbook_types": [
    "investigation",
    "remediation"
  ],
  "workflow_start": "start--1",
  "workflow": {
    "start--1": {
      "type": "start",
      "on_completion": "action--1"
    },
    "action--1": {
      "type": "action",
      "name": "Alert Ingestion",
      "description": "System received new raw SIEM log",
      "executed_at": "2026-04-03T20:17:28.442463",
      "on_completion": "action--2"
    },
    "action--2": {
      "type": "action",
      "name": "Blocked IP 192.168.1.32",
      "description": "High severity threat detected",
      "executed_at": "2026-04-03T20:17:28.444599",
      "on_completion": "end--2"
    },
    "end--2": {
      "type": "end"
    }
  }
}